pandas_cacher/__init__.py
pandas_cacher/pandas_cache.py
pandas_cacher-0.1.3.dist-info/WHEEL
pandas_cacher-0.1.3.dist-info/METADATA
pandas_cacher-0.1.3.dist-info/RECORD
