Metadata-Version: 2.1
Name: pandas-cacher
Version: 0.1.3
Summary: Pandas cacher
Author: Statnett Datascience
Author-email: Datascience.Drift@statnett.no
Requires-Python: >=3.6,<4.0
Classifier: Programming Language :: Python :: 3
Classifier: Programming Language :: Python :: 3.6
Classifier: Programming Language :: Python :: 3.7
Classifier: Programming Language :: Python :: 3.8
Requires-Dist: h5py (>=2.10.0,<3.0.0)
Requires-Dist: numpy
Requires-Dist: pandas
Requires-Dist: tables
